Accuinsight/__about__.py
Accuinsight/__init__.py
Accuinsight/exceptions.py
Accuinsight/info.py
Accuinsight/Lifecycle/ML.py
Accuinsight/Lifecycle/MakeAiruntimeModel.py
Accuinsight/Lifecycle/__init__.py
Accuinsight/Lifecycle/common.py
Accuinsight/Lifecycle/keras.py
Accuinsight/Lifecycle/model_evaluation.py
Accuinsight/Lifecycle/settings.py
Accuinsight/Lifecycle/tensorflow.py
Accuinsight/Lifecycle/utils.py
Accuinsight/Monitoring/__init__.py
Accuinsight/Monitoring/deploy/__init__.py
Accuinsight/Monitoring/deploy/monitoring_deploy.py
Accuinsight/PackageList/__init__.py
Accuinsight/PackageList/package_list.py
Accuinsight/WorkspaceRun/__init__.py
Accuinsight/WorkspaceRun/workspace_run.py
Accuinsight/modeler/__init__.py
Accuinsight/modeler/exceptions.py
Accuinsight/modeler/info.py
Accuinsight/modeler/clients/__init__.py
Accuinsight/modeler/clients/modeler_api.py
Accuinsight/modeler/clients/modeler_api_common.py
Accuinsight/modeler/core/Lifecycle.py
Accuinsight/modeler/core/ModelType.py
Accuinsight/modeler/core/__init__.py
Accuinsight/modeler/core/calculation_metrics.py
Accuinsight/modeler/core/feature_contribution.py
Accuinsight/modeler/core/func.py
Accuinsight/modeler/core/func_for_visual.py
Accuinsight/modeler/core/get.py
Accuinsight/modeler/core/get_for_visual.py
Accuinsight/modeler/core/lossFuncInfo.py
Accuinsight/modeler/core/metricsLightgbm.py
Accuinsight/modeler/core/path.py
Accuinsight/modeler/core/sklearnModelType.py
Accuinsight/modeler/core/workspace_run_log.py
Accuinsight/modeler/core/LcConst/LcConst.py
Accuinsight/modeler/core/LcConst/__init__.py
Accuinsight/modeler/core/MonitoringConst/__init__.py
Accuinsight/modeler/core/MonitoringConst/deploy/DeployConst.py
Accuinsight/modeler/core/MonitoringConst/deploy/__init__.py
Accuinsight/modeler/core/Run/RunOjbject.py
Accuinsight/modeler/core/Run/__init__.py
Accuinsight/modeler/core/Run/ParseRun/BaseParser.py
Accuinsight/modeler/core/Run/ParseRun/ParseExperiment.py
Accuinsight/modeler/core/Run/ParseRun/ParseKeras.py
accuinsight-3.6.20251218.dist-info/licenses/LICENSE.txt
accuinsight-3.6.20251218.dist-info/METADATA
accuinsight-3.6.20251218.dist-info/WHEEL
accuinsight-3.6.20251218.dist-info/top_level.txt
accuinsight-3.6.20251218.dist-info/RECORD
