Metadata-Version: 2.4
Name: Accuinsight
Version: 3.6.20251218
Summary: Model life cycle and monitoring library in Accuinsight+
Home-page: 
Author: Twolinecloud
Classifier: Development Status :: 1 - Planning
Classifier: Intended Audience :: Science/Research
Classifier: Natural Language :: English
Classifier: Operating System :: OS Independent
Classifier: Programming Language :: Python :: 3.5
Classifier: Programming Language :: Python :: 3.6
Classifier: Programming Language :: Python :: 3.7
Classifier: Topic :: Utilities
Classifier: Topic :: Scientific/Engineering
Classifier: Topic :: Scientific/Engineering :: Artificial Intelligence
Classifier: Topic :: Software Development :: Libraries :: Python Modules
Classifier: License :: OSI Approved :: MIT License
License-File: LICENSE.txt
Requires-Dist: wrapt>=1.15.0
Requires-Dist: numpy<2.0.0,>=1.26.0
Requires-Dist: pandas>=2.0.3
Requires-Dist: scipy
Requires-Dist: scikit-learn==1.2.2
Requires-Dist: matplotlib>=3.7.1
Requires-Dist: joblib>=1.2.0
Requires-Dist: py-cpuinfo>=9.0.0
Requires-Dist: requests
Requires-Dist: gorilla==0.3.0
Requires-Dist: more-itertools
Requires-Dist: packaging
Requires-Dist: GitPython
Requires-Dist: munch
Requires-Dist: nest-asyncio
Requires-Dist: cython
Requires-Dist: lightgbm
Requires-Dist: boto3
Requires-Dist: shap
Requires-Dist: numba
Dynamic: author
Dynamic: classifier
Dynamic: description
Dynamic: license-file
Dynamic: requires-dist
Dynamic: summary
